README.md
setup.cfg
setup.py
blackiceprog/__init__.py
blackiceprog/__main__.py
blackiceprog.egg-info/PKG-INFO
blackiceprog.egg-info/SOURCES.txt
blackiceprog.egg-info/dependency_links.txt
blackiceprog.egg-info/entry_points.txt
blackiceprog.egg-info/requires.txt
blackiceprog.egg-info/top_level.txt