Metadata-Version: 1.0
Name: blackiceprog
Version: 2.0.0
Summary: Programmer for the blackice FPGAs by myStorm (https://mystorm.uk/)
Home-page: https://github.com/jpenalbae/black-iceprog
Author: Jaime Penalba Estebanez
Author-email: jpenalbae@gmail.com
License: GNU General Public License v3.0
Keywords: fpga,blackice,programmer,bitstream,mystorm
Platform: UNKNOWN
